aiohttp-rapid/__init__.py
rapid/__init__.py
aiohttp_rapid-0.0.0.dist-info/LICENSE
aiohttp_rapid-0.0.0.dist-info/METADATA
aiohttp_rapid-0.0.0.dist-info/WHEEL
aiohttp_rapid-0.0.0.dist-info/top_level.txt
aiohttp_rapid-0.0.0.dist-info/RECORD
