Metadata-Version: 2.1
Name: aiohttp-rapid
Version: 0.0.0
Summary: Aiohttp rapid
Home-page: https://github.com/unocongafas/rapid
Author: Alejandro Castaño González
Author-email: unocongafas@gmail.com
License: UNKNOWN
Platform: UNKNOWN
Classifier: Development Status :: 1 - Planning
Classifier: Environment :: Web Environment
Classifier: Intended Audience :: Developers
Classifier: License :: OSI Approved :: Apache Software License
Classifier: Natural Language :: Spanish
Classifier: Operating System :: OS Independent
Classifier: Programming Language :: Python :: 3
Classifier: Programming Language :: Python :: 3.8
Classifier: Topic :: Internet :: WWW/HTTP :: HTTP Servers
Classifier: Topic :: Software Development :: Libraries :: Application Frameworks
Requires-Python: >=3.8
Requires-Dist: aiodns (==2.0.0)
Requires-Dist: aiohttp (==3.6.2)
Requires-Dist: aiojobs (==0.2.2)
Requires-Dist: async-timeout (==3.0.1)
Requires-Dist: attrs (==20.2.0)
Requires-Dist: cchardet (==2.1.6)
Requires-Dist: cffi (==1.14.3)
Requires-Dist: chardet (==3.0.4)
Requires-Dist: idna (==2.10)
Requires-Dist: multidict (==4.7.6)
Requires-Dist: pycares (==3.1.1)
Requires-Dist: pycparser (==2.20)
Requires-Dist: ujson (==4.0.0)
Requires-Dist: yarl (==1.6.0)
